exasol/slc_ci_setup/cli/__init__.py
exasol/slc_ci_setup/cli/cli.py
exasol/slc_ci_setup/cli/commands/__init__.py
exasol/slc_ci_setup/cli/commands/deploy_cd_build.py
exasol/slc_ci_setup/cli/commands/deploy_ci_build.py
exasol/slc_ci_setup/cli/commands/deploy_nightly_build.py
exasol/slc_ci_setup/cli/main.py
exasol/slc_ci_setup/lib/deploy_build.py
exasol/slc_ci_setup/lib/template_access.py
exasol/slc_ci_setup/nox/tasks.py
exasol/slc_ci_setup/templates/heading.tmpl
exasol/slc_ci_setup/templates/slc_cd.yml.tmpl
exasol/slc_ci_setup/templates/slc_cd_flavor.yml.tmpl
exasol/slc_ci_setup/templates/slc_cd_self_check.yml.tmpl
exasol/slc_ci_setup/templates/slc_ci.yml.tmpl
exasol/slc_ci_setup/templates/slc_ci_build_slc.yml.tmpl
exasol/slc_ci_setup/templates/slc_ci_check_for_build.yml.tmpl
exasol/slc_ci_setup/templates/slc_ci_flavor.yml.tmpl
exasol/slc_ci_setup/templates/slc_ci_prepare_test_container.yml.tmpl
exasol/slc_ci_setup/templates/slc_ci_self_check.yml.tmpl
exasol/slc_ci_setup/templates/slc_ci_test_slc.yml.tmpl
exasol/slc_ci_setup/templates/slc_nightly.yml.tmpl
exasol/slc_ci_setup/templates/slc_nightly_flavor.yml.tmpl
exasol/slc_ci_setup/templates/slc_nightly_self_check.yml.tmpl
exasol/slc_ci_setup/version.py
exasol_script_languages_container_ci_setup-3.4.0.dist-info/LICENSE
exasol_script_languages_container_ci_setup-3.4.0.dist-info/METADATA
exasol_script_languages_container_ci_setup-3.4.0.dist-info/WHEEL
exasol_script_languages_container_ci_setup-3.4.0.dist-info/entry_points.txt
exasol_script_languages_container_ci_setup-3.4.0.dist-info/RECORD
